get_browser_cookies/__init__.py
get_browser_cookies/cli.py
get_browser_cookies/version.py
get_browser_cookies-0.1.1.dist-info/LICENSE
get_browser_cookies-0.1.1.dist-info/METADATA
get_browser_cookies-0.1.1.dist-info/WHEEL
get_browser_cookies-0.1.1.dist-info/entry_points.txt
get_browser_cookies-0.1.1.dist-info/top_level.txt
get_browser_cookies-0.1.1.dist-info/RECORD
