Metadata-Version: 2.1
Name: get-browser-cookies
Version: 0.1.1
Summary: CLI for .
Home-page: https://github.com/AlJohri/get-browser-cookies
Author: Al Johri
Author-email: al.johri@gmail.com
License: MIT
Platform: UNKNOWN
Classifier: Programming Language :: Python :: 3 :: Only
Classifier: License :: OSI Approved :: MIT License
License-File: LICENSE
Requires-Dist: browser-cookie3
